llama_index/embeddings/deepinfra/__init__.py
llama_index/embeddings/deepinfra/base.py
llama_index_embeddings_deepinfra-0.4.1.dist-info/METADATA
llama_index_embeddings_deepinfra-0.4.1.dist-info/WHEEL
llama_index_embeddings_deepinfra-0.4.1.dist-info/licenses/LICENSE
llama_index_embeddings_deepinfra-0.4.1.dist-info/RECORD
