Metadata-Version: 2.4
Name: llama-index-embeddings-deepinfra
Version: 0.4.1
Summary: llama-index embeddings deepinfra integration
Author-email: Oguz Vuruskaner <oguzvuruskaner@gmail.com>
License-Expression: MIT
License-File: LICENSE
Requires-Python: <4.0,>=3.9
Requires-Dist: aiohttp<4,>=3.8.1
Requires-Dist: llama-index-core<0.15,>=0.13.0
